{
  "artifact_id": "source_artifact_f0e9d84c3dfd45e8",
  "byte_size": 981831,
  "columns": [
    "uid",
    "b_visit",
    "b_pol_handling",
    "b_safety",
    "e_urja_knowledge",
    "e_visit",
    "e_pol_handling",
    "e_safety",
    "spw",
    "e_gender",
    "hh_id",
    "member_gender",
    "ps_code",
    "population",
    "urban",
    "dist_urban",
    "strat_pca",
    "treatment",
    "group",
    "dist_id",
    "implement_quality",
    "training_score",
    "comm_outreach_strength",
    "regular_whd",
    "women_whd",
    "attrited"
  ],
  "estimated_data_rows": 6519,
  "file_name": "citizen_full_data.tab",
  "file_type": "tab",
  "local_path": "data/raw/corpus_candidates/political_science_unlock/dataverse/R75XVZ/citizen_full_data.tab",
  "parent_corpus_database_id": "raw_corpus:political_science_unlock",
  "preview_rows": [
    {
      "attrited": 0.0,
      "b_pol_handling": 0.44444445,
      "b_safety": 3.6666667,
      "b_visit": 0.0,
      "comm_outreach_strength": 2.15,
      "dist_id": 3000.0,
      "dist_urban": 4.0,
      "e_gender": 1.0,
      "e_pol_handling": 0.5,
      "e_safety": 4.0,
      "e_urja_knowledge": 0.0,
      "e_visit": 0.0,
      "group": "regular mhd",
      "hh_id": 1051201.0,
      "implement_quality": 7.0,
      "member_gender": 1.0,
      "population": 107000,
      "ps_code": 3023.0,
      "regular_whd": 1.0,
      "spw": 0.0015256205,
      "strat_pca": -0.0042945286,
      "training_score": 3.7179487,
      "treatment": 1,
      "uid": 10512011,
      "urban": 1.0,
      "women_whd": 0.0
    },
    {
      "attrited": 1.0,
      "b_pol_handling": 0.0,
      "b_safety": 3.6666667,
      "b_visit": 0.0,
      "comm_outreach_strength": 2.15,
      "dist_id": 3000.0,
      "dist_urban": 4.0,
      "e_gender": null,
      "e_pol_handling": null,
      "e_safety": null,
      "e_urja_knowledge": null,
      "e_visit": null,
      "group": "regular mhd",
      "hh_id": 1051202.0,
      "implement_quality": 7.0,
      "member_gender": 1.0,
      "population": 107000,
      "ps_code": 3023.0,
      "regular_whd": 1.0,
      "spw": 0.0015256205,
      "strat_pca": -0.0042945286,
      "training_score": 3.7179487,
      "treatment": 1,
      "uid": 10512021,
      "urban": 1.0,
      "women_whd": 0.0
    },
    {
      "attrited": 0.0,
      "b_pol_handling": -0.11111111,
      "b_safety": 2.3333333,
      "b_visit": 0.0,
      "comm_outreach_strength": 2.15,
      "dist_id": 3000.0,
      "dist_urban": 4.0,
      "e_gender": 1.0,
      "e_pol_handling": 0.25,
      "e_safety": 2.0,
      "e_urja_knowledge": 0.0,
      "e_visit": 0.0,
      "group": "regular mhd",
      "hh_id": 1051203.0,
      "implement_quality": 7.0,
      "member_gender": 1.0,
      "population": 107000,
      "ps_code": 3023.0,
      "regular_whd": 1.0,
      "spw": 0.0015256205,
      "strat_pca": -0.0042945286,
      "training_score": 3.7179487,
      "treatment": 1,
      "uid": 10512031,
      "urban": 1.0,
      "women_whd": 0.0
    },
    {
      "attrited": 0.0,
      "b_pol_handling": -0.2,
      "b_safety": 3.6666667,
      "b_visit": 0.0,
      "comm_outreach_strength": 2.15,
      "dist_id": 3000.0,
      "dist_urban": 4.0,
      "e_gender": 1.0,
      "e_pol_handling": null,
      "e_safety": 3.0,
      "e_urja_knowledge": 0.0,
      "e_visit": 0.0,
      "group": "regular mhd",
      "hh_id": 1051204.0,
      "implement_quality": 7.0,
      "member_gender": 1.0,
      "population": 107000,
      "ps_code": 3023.0,
      "regular_whd": 1.0,
      "spw": 0.0015256205,
      "strat_pca": -0.0042945286,
      "training_score": 3.7179487,
      "treatment": 1,
      "uid": 10512041,
      "urban": 1.0,
      "women_whd": 0.0
    },
    {
      "attrited": 1.0,
      "b_pol_handling": 0.0,
      "b_safety": 3.3333333,
      "b_visit": 0.0,
      "comm_outreach_strength": 2.15,
      "dist_id": 3000.0,
      "dist_urban": 4.0,
      "e_gender": null,
      "e_pol_handling": null,
      "e_safety": null,
      "e_urja_knowledge": null,
      "e_visit": null,
      "group": "regular mhd",
      "hh_id": 1051205.0,
      "implement_quality": 7.0,
      "member_gender": 1.0,
      "population": 107000,
      "ps_code": 3023.0,
      "regular_whd": 1.0,
      "spw": 0.0015256205,
      "strat_pca": -0.0042945286,
      "training_score": 3.7179487,
      "treatment": 1,
      "uid": 10512051,
      "urban": 1.0,
      "women_whd": 0.0
    }
  ],
  "sample_kind": "delimited_table",
  "sample_row_count": 5,
  "sampled_at": "2026-05-04T00:20:31",
  "sha256": "1043954e40f5debe79c8648845434e86c348982b402dbe9e217c2975048ea2ca"
}