{
  "artifact_id": "source_artifact_76088f003b4d76fc",
  "byte_size": 93062,
  "columns": [
    "author",
    "phd",
    "phd_date"
  ],
  "file_name": "supp_data_authors.dta",
  "file_type": "dta",
  "local_path": "data/raw/corpus_candidates/brodeur_star_wars_openicpsr/full_project/brodeur_le_sangnier_zylberberg_replication/Data/Temp/supp_data_authors.dta",
  "parent_corpus_database_id": "raw_corpus:brodeur_star_wars_openicpsr",
  "preview_rows": [
    {
      "author": "A. Joshua Strickland",
      "phd": "Unknown",
      "phd_date": null
    },
    {
      "author": "Aaron S. Edlin",
      "phd": "Princeton",
      "phd_date": "1993.0"
    },
    {
      "author": "Aaron Tornell",
      "phd": "MIT",
      "phd_date": "1987.0"
    },
    {
      "author": "Abdul Abiad",
      "phd": "University of Pennsylvania",
      "phd_date": "2002.0"
    },
    {
      "author": "Abhijit Banerjee",
      "phd": "Harvard University",
      "phd_date": "1988.0"
    }
  ],
  "sample_kind": "stata",
  "sample_row_count": 5,
  "sampled_at": "2026-05-04T00:20:17",
  "sha256": "437fb91cec0ef720651abde0ebdedced75c8c73113407fb59ac4982bd1212dc6"
}