{
  "artifact_id": "source_artifact_7aa29d359ac34e70",
  "byte_size": 7414273,
  "columns": [
    "paper_id",
    "pdf_filename_x",
    "internal_note",
    "claim_decision",
    "version",
    "claim2_abstract",
    "coded_claim2",
    "claim2_pg",
    "claim2_start",
    "claim2_box",
    "pdf_filename_y",
    "trace_n",
    "p1_equivalent",
    "claim2_id",
    "ta2_claim2_id",
    "ta3_claim2_id",
    "claim3_hyp",
    "coded_claim3",
    "claim3_pg",
    "claim3_start",
    "claim3_box",
    "claim3_id",
    "ta2_claim3_id",
    "ta3_claim3_id",
    "claim4_result",
    "coded_claim4",
    "claim4_pg",
    "claim4_start",
    "claim4_box",
    "focal",
    "focal_sample",
    "claim4_id",
    "ta2_claim4_id",
    "ta3_claim4_id",
    "stat_evidence",
    "stat_evidence_box",
    "stat_evidence_pg",
    "stat_evidence_start",
    "coded_stat_evidence",
    "stat_evidence_id",
    "ta2_stat_evidence_id",
    "ta3_stat_evidence_id"
  ],
  "estimated_data_rows": 5808,
  "file_name": "orig_claims_p2-bushel.csv",
  "file_type": "csv",
  "local_path": "data/raw/source_artifacts/figure1/score/source_artifact_7aa29d359ac34e70__orig_claims_p2-bushel.csv",
  "parent_corpus_database_id": "score",
  "preview_rows": [
    {
      "claim2_abstract": "In three experiments inducing a detailed versus abstract processing style using perceptual (Experiment 1), motivational (Experiment 2), and social (Experiment 3) manipulations, we found that empathic concerns are enhanced in contexts associated with a more detailed processing style (i.e., local perceptual scope, prevention motivation, and low power, respectively).",
      "claim2_box": "(x1: 198.14 y1: 297.88) (x2: 334.95 y2: 330.98)",
      "claim2_id": "p7x3l9",
      "claim2_pg": 1,
      "claim2_start": 1024,
      "claim3_box": "(x1: 182.49 y1: 111.04) (x2: 131.52 y2: 157.84)",
      "claim3_hyp": "Because empathic concern requires self-other differentiation and representations of concrete other-oriented emotions, we expected that participants' empathic concern would be facilitated when primed with a local (as opposed to a global perceptual) scope.",
      "claim3_id": "z7bmwo",
      "claim3_pg": 3,
      "claim3_start": 342,
      "claim4_box": "(x1: 45.69 y1: 633.86) (x2: 284.78 y2: 659.68) | (x1: 301.72 y1: 58.77) (x2: 500.47 y2: 105.51)",
      "claim4_id": "m75zng",
      "claim4_pg": "3 | 3",
      "claim4_result": "A significant omnibus ANOVA revealed that the priming manip- ulation inﬂuenced participants' empathic concern, F(1,38)=3.73, p= .033, ηp² = .16. In line with predictions, follow-up contrasts | indicated that participants in the local priming condition reported greater empathic concern (M=3.31, SD=0.40) than participants in the global priming (M=3.00, SD=0.25) or in the control condition (M=3.05, SD=0.27), F(1,39)=7.28, p= .010, ηp² = .16, whereas the latter two conditions did not differ (Fb1; see Table 1).",
      "claim4_start": "2980 | 3471",
      "claim_decision": "Pass",
      "coded_claim2": null,
      "coded_claim3": null,
      "coded_claim4": "A significant omnibus ANOVA revealed that the priming manipulation influenced participants' empathic concern, F(1,38) = 3.73, p = .033, partial eta-squared = .16. In line with predictions, follow-up contrasts indicated that participants in the local priming condition reported greater empathic concern (M = 3.31, SD = 0.40) than participants in the global priming (M = 3.00, SD = 0.25) or in the control condition (M = 3.05, SD = 0.27), F(1,39) = 7.28, p = .010, partial eta-squared = .16, whereas the latter two conditions did not differ (F<1; see Table 1).",
      "coded_stat_evidence": "F(1,38) = 3.73, p = .033, partial eta-squared = .16; F(1,39) = 7.28, p = .010, partial eta-squared = .16; F<1",
      "focal": true,
      "focal_sample": null,
      "internal_note": null,
      "p1_equivalent": false,
      "paper_id": "Wre",
      "pdf_filename_x": "Woltin_JournExpSocPsych_2011_Wre",
      "pdf_filename_y": "Woltin_JournExpSocPsych_2011_Wre",
      "stat_evidence": "F(1,38)=3.73, p= .033, ηp² = .16 | F(1,39)=7.28, p= .010, ηp² = .16 | Fb1",
      "stat_evidence_box": "(x1: 231.31 y1: 644.42) (x2: 102.84 y2: 659.68) | (x1: 383.36 y1: 90.24) (x2: 504.57 y2: 95.02) | (x1: 434.78 y1: 100.74) (x2: 449.54 y2: 105.51)",
      "stat_evidence_id": "xv9zy2",
      "stat_evidence_pg": "3 | 3 | 3",
      "stat_evidence_start": "3091 | 3687 | 3771",
      "ta2_claim2_id": "z73yv8",
      "ta2_claim3_id": "4731yj",
      "ta2_claim4_id": "x736v8",
      "ta2_stat_evidence_id": "zvd54z",
      "ta3_claim2_id": "m73z9o",
      "ta3_claim3_id": "173mlj",
      "ta3_claim4_id": "573o9m",
      "ta3_stat_evidence_id": "qvg5mq",
      "trace_n": 1,
      "version": 1
    },
    {
      "claim2_abstract": "In three experiments inducing a detailed versus abstract processing style using perceptual (Experiment 1), motivational (Experiment 2), and social (Experiment 3) manipulations, we found that empathic concerns are enhanced in contexts associated with a more detailed processing style (i.e., local perceptual scope, prevention motivation, and low power, respectively).",
      "claim2_box": "(x1: 198.14 y1: 297.88) (x2: 334.95 y2: 330.98)",
      "claim2_id": "p7x3l9",
      "claim2_pg": 1,
      "claim2_start": 1024,
      "claim3_box": "(x1: 505.47 y1: 249.59) (x2: 480.82 y2: 306.82)",
      "claim3_hyp": "We reasoned that the detailed, concrete processing style induced by a prevention focus would facilitate ‘zooming in’ on concrete, other-oriented emotions in participants (i.e., would increase empathic concern) as compared to the abstract, holistic processing style associated with\n\n‘zooming out’ and induced by a promotion focus.",
      "claim3_id": "omwvr9",
      "claim3_pg": 3,
      "claim3_start": 4539,
      "claim4_box": "(x1: 313.68 y1: 581.53) (x2: 448.88 y2: 628.27)",
      "claim4_id": "bzr68m",
      "claim4_pg": "3",
      "claim4_result": "An ANOVA revealed that regulatory focus inﬂuenced participants' empathic concern, F(1,38)=5.40, p= .026, ηp² = .12 . As predicted, participants manifested a greater empathic concern when primed with prevention (M=4.26, SD=0.45) rather than with promotion focus (M=3.88, SD=0.59; see Table 1).",
      "claim4_start": "5916",
      "claim_decision": "Pass",
      "coded_claim2": null,
      "coded_claim3": null,
      "coded_claim4": "An ANOVA revealed that regulatory focus influenced participants' empathic concern, F(1,38)=5.40, p=.026, partial eta-squared = .12 . As predicted, participants manifested a greater empathic concern when primed with prevention (M=4.26, SD=0.45) rather than with promotion focus (M=3.88, SD=0.59; see Table 1).",
      "coded_stat_evidence": "F(1,38)=5.40, p=.026, partial eta-squared = .12",
      "focal": true,
      "focal_sample": null,
      "internal_note": null,
      "p1_equivalent": false,
      "paper_id": "Wre",
      "pdf_filename_x": "Woltin_JournExpSocPsych_2011_Wre",
      "pdf_filename_y": "Woltin_JournExpSocPsych_2011_Wre",
      "stat_evidence": "F(1,38)=5.40, p= .026, ηp² = .12",
      "stat_evidence_box": "(x1: 372.70 y1: 592.14) (x2: 496.35 y2: 596.92)",
      "stat_evidence_id": "xl8gz2",
      "stat_evidence_pg": "3",
      "stat_evidence_start": "5998",
      "ta2_claim2_id": "z73yv8",
      "ta2_claim3_id": "q15ozj",
      "ta2_claim4_id": "x6bv78",
      "ta2_stat_evidence_id": "zl9o3z",
      "ta3_claim2_id": "m73z9o",
      "ta3_claim3_id": "nm2vxj",
      "ta3_claim4_id": "5ox4l5",
      "ta3_stat_evidence_id": "ql9oyq",
      "trace_n": 2,
      "version": 1
    },
    {
      "claim2_abstract": "In three experiments inducing a detailed versus abstract processing style using perceptual (Experiment 1), motivational (Experiment 2), and social (Experiment 3) manipulations, we found that empathic concerns are enhanced in contexts associated with a more detailed processing style (i.e., local perceptual scope, prevention motivation, and low power, respectively).",
      "claim2_box": "(x1: 198.14 y1: 297.88) (x2: 334.95 y2: 330.98)",
      "claim2_id": "p7x3l9",
      "claim2_pg": 1,
      "claim2_start": 1024,
      "claim3_box": "(x1: 68.54 y1: 202.60) (x2: 170.18 y2: 238.90)",
      "claim3_hyp": "Based on these finding, and research showing a link between low power and differentiation processes (Förster, 2009), we predicted that the detailed, concrete processing style associated with low power should facilitate empathic concern.",
      "claim3_id": "9pg6q9",
      "claim3_pg": 4,
      "claim3_start": 770,
      "claim4_box": "(x1: 54.48 y1: 560.90) (x2: 74.25 y2: 607.64)",
      "claim4_id": "glpd9b",
      "claim4_pg": "4",
      "claim4_result": "An ANOVA revealed that power priming inﬂuenced participants' empathic concern, F(1,34)=5.76, p= .022, ηp² = .15. As predicted, participants reported greater empathic concern when primed with low (M=3.89, SD=0.45) than high power (M=3.47, SD=0.59; see Table 1).",
      "claim4_start": "2238",
      "claim_decision": "Pass",
      "coded_claim2": null,
      "coded_claim3": null,
      "coded_claim4": "An ANOVA revealed that power priming influenced participants' empathic concern, F(1,34)=5.76, p=.022, partial eta-squared = .15. As predicted, participants reported greater empathic concern when primed with low (M=3.89, SD=0.45) than high power (M=3.47, SD=0.59; see Table 1).",
      "coded_stat_evidence": "F(1,34)=5.76, p=.022, partial eta-squared = .15",
      "focal": true,
      "focal_sample": null,
      "internal_note": null,
      "p1_equivalent": true,
      "paper_id": "Wre",
      "pdf_filename_x": "Woltin_JournExpSocPsych_2011_Wre",
      "pdf_filename_y": "Woltin_JournExpSocPsych_2011_Wre",
      "stat_evidence": "F(1,34)=5.76, p= .022, ηp² = .15",
      "stat_evidence_box": "(x1: 114.57 y1: 571.51) (x2: 239.25 y2: 576.29)",
      "stat_evidence_id": "2db4lx",
      "stat_evidence_pg": "4",
      "stat_evidence_start": "2317",
      "ta2_claim2_id": "z73yv8",
      "ta2_claim3_id": "qxlvrq",
      "ta2_claim4_id": "8mgvq8",
      "ta2_stat_evidence_id": "xp4gmx",
      "ta3_claim2_id": "m73z9o",
      "ta3_claim3_id": "1zrbpn",
      "ta3_claim4_id": "m12p45",
      "ta3_stat_evidence_id": "q27b5p",
      "trace_n": 3,
      "version": 1
    },
    {
      "claim2_abstract": "In three experiments inducing a detailed versus abstract processing style using perceptual (Experiment 1), motivational (Experiment 2), and social (Experiment 3) manipulations, we found that empathic concerns are enhanced in contexts associated with a more detailed processing style (i.e., local perceptual scope, prevention motivation, and low power, respectively).",
      "claim2_box": "(x1: 198.14 y1: 297.88) (x2: 334.95 y2: 330.98)",
      "claim2_id": "p7x3l9",
      "claim2_pg": 1,
      "claim2_start": 1024,
      "claim3_box": "(x1: 286.35 y1: 634.14) (x2: 239.35 y2: 680.88)",
      "claim3_hyp": "In this fourth experiment (N=41; 32 females) the procedure followed the previous power-experiment, but we now primed power by having participants recall a situation in which they had power over someone else or in which someone else had power over them",
      "claim3_id": "zydmqz",
      "claim3_pg": 4,
      "claim3_start": 2686,
      "claim4_box": "(x1: 95.02 y1: 696.90) (x2: 110.57 y2: 743.64)",
      "claim4_id": "b64v8m",
      "claim4_pg": "4",
      "claim4_result": "Using this alternative manipulation of power and a mixed sample indeed replicated our previous findings: low-power participants reported greater empathic concern (M=4.02, SD=0.58) than high-power participants (M=3.83, SD=0.55), F(1,39)=5.867, p= .020, ηp² = .13.",
      "claim4_start": "3038",
      "claim_decision": "Pass",
      "coded_claim2": null,
      "coded_claim3": null,
      "coded_claim4": "Using this alternative manipulation of power and a mixed sample indeed replicated our previous findings: low-power participants reported greater empathic concern (M=4.02, SD=0.58) than high-power participants (M=3.83, SD=0.55), F(1,39)=5.867, p=.020, partial eta-squared = .13.",
      "coded_stat_evidence": "F(1,39)=5.867, p=.020, partial eta-squared = .13",
      "focal": true,
      "focal_sample": null,
      "internal_note": null,
      "p1_equivalent": false,
      "paper_id": "Wre",
      "pdf_filename_x": "Woltin_JournExpSocPsych_2011_Wre",
      "pdf_filename_y": "Woltin_JournExpSocPsych_2011_Wre",
      "stat_evidence": "F(1,39)=5.867, p= .020, ηp² = .13",
      "stat_evidence_box": "(x1: 235.50 y1: 728.38) (x2: 108.74 y2: 743.64)",
      "stat_evidence_id": "xmgwmx",
      "stat_evidence_pg": "4",
      "stat_evidence_start": "3266",
      "ta2_claim2_id": "z73yv8",
      "ta2_claim3_id": "4m5vzq",
      "ta2_claim4_id": "x42wk1",
      "ta2_stat_evidence_id": "z4458z",
      "ta3_claim2_id": "m73z9o",
      "ta3_claim3_id": "nbgv71",
      "ta3_claim4_id": "54lw2m",
      "ta3_stat_evidence_id": "qyn274",
      "trace_n": 4,
      "version": 1
    },
    {
      "claim2_abstract": "These daring proclivities do not appear driven by impaired affect or self-esteem.",
      "claim2_box": "(x1: 509.80 y1: 264.33) (x2: 506.91 y2: 277.91)",
      "claim2_id": "pg5ybx",
      "claim2_pg": 1,
      "claim2_start": 574,
      "claim3_box": "(x1: 227.56 y1: 546.31) (x2: 121.07 y2: 584.75)",
      "claim3_hyp": "to document the direct and unique impact of social exclusion on financial risk-taking, our work will attempt to disentangle affect from social exclusion.",
      "claim3_id": "zjlvb6",
      "claim3_pg": 3,
      "claim3_start": 2333,
      "claim4_box": "(x1: 280.34 y1: 314.09) (x2: 150.89 y2: 341.57) | (x1: 154.08 y1: 336.01) (x2: 236.91 y2: 352.53)",
      "claim4_id": "g8r4od",
      "claim4_pg": "5 | 5",
      "claim4_result": "ex- cluded participants did not differ from their negative-mood counterparts in terms of | affect in general (Mexcl p 2.59 vs. Mneg.mood p 2.89; F(1, 164) p 2.51, p 1 .11)",
      "claim4_start": "1378 | 1467",
      "claim_decision": "Pass",
      "coded_claim2": null,
      "coded_claim3": null,
      "coded_claim4": "...excluded participants did not differ from their negative-mood counterparts in terms of affect in general (M_excl = 2.59 vs. M_neg.mood = 2.89; F(1, 164) = 2.51, p > .11)...",
      "coded_stat_evidence": "M_excl = 2.59 vs. M_neg.mood = 2.89; F(1, 164) = 2.51, p > .11",
      "focal": true,
      "focal_sample": null,
      "internal_note": "In Claim 2 \"Rather, interpersonal rejection exacerbates financial risk-taking by heightening the instrumentality of money (as a substitute for popularity) to obtain benefits in life.\" there are two statements: (1) \"interpersonal rejection exacerbates financial risk-taking\" and (2) a statement of a mediation effect via instrumentality of money",
      "p1_equivalent": false,
      "paper_id": "BaDx",
      "pdf_filename_x": "Duclos_JournConsRes_2013_BaDx",
      "pdf_filename_y": "Duclos_JournConsRes_2013_BaDx",
      "stat_evidence": "(Mexcl p 2.59 vs. Mneg.mood p 2.89; F(1, 164) p 2.51, p 1 .11)",
      "stat_evidence_box": "(x1: 223.29 y1: 336.01) (x2: 236.91 y2: 352.53)",
      "stat_evidence_id": "266mod",
      "stat_evidence_pg": "5",
      "stat_evidence_start": "1485",
      "ta2_claim2_id": "l55xqp",
      "ta2_claim3_id": "4gro2m",
      "ta2_claim4_id": "xj5m3j",
      "ta2_stat_evidence_id": "x3k718",
      "ta3_claim2_id": "l54xq5",
      "ta3_claim3_id": "1glo8z",
      "ta3_claim4_id": "5jx13o",
      "ta3_stat_evidence_id": "p3b7rg",
      "trace_n": 1,
      "version": 1
    }
  ],
  "sample_kind": "delimited_table",
  "sample_row_count": 5,
  "sampled_at": "2026-05-02T13:11:33",
  "sha256": "30f3d4bec0692845ccf5de86cbcf22fec6fb1cec2afd59d499857301e0c35998"
}