{
  "artifact_id": "source_artifact_3b8d64bbe4d7e2e0",
  "byte_size": 545,
  "file_name": "countTrialxCondition.R",
  "file_type": "r",
  "line_preview": [
    "countTrialxCondition <- function (database){",
    "  # this function counts the number of trial per condition of interest",
    "  ",
    "  # init counters",
    "  count_val   = 0;",
    "  count_deval = 0;",
    "  ",
    "  for (i in 1:length(database$prepost)) {",
    "    ",
    "    if (database$cue[i] == 'valued') {",
    "      count_val = count_val + 1",
    "      database$itemxcondition[i] = count_val",
    "      ",
    "    } else if (database$cue[i] == 'devalued') {",
    "      count_deval = count_deval + 1",
    "      database$itemxcondition[i] = count_deval",
    "      ",
    "    }",
    "    ",
    "  }",
    "  return (database)  ",
    "}"
  ],
  "line_preview_count": 22,
  "local_path": "data/raw/source_artifacts/figure1_acquisition_tabular_first/repo_search_osf_2b928c9c5eb3/source_artifact_3b8d64bbe4d7e2e0__countTrialxCondition.R",
  "parent_corpus_database_id": "repo_search_osf_2b928c9c5eb3",
  "sample_kind": "text",
  "sampled_at": "2026-05-01T22:32:49",
  "sha256": "54fb091bd8e32394c7cf03edb36515e1e9a363775cc057cd751c11ca4a6f2d18"
}